[
    {
        "timestamp": "2024-02-19T17:12:43.252216",
        "total_eval_time": 4453.648949302733,
        "chromosome": [
            2.003576059446601,
            1.4285747815280418,
            0.17314944132831897,
            0.03088572368347238,
            1.0405422730236056,
            1.8827994473636125,
            0.4404722736263469
        ],
        "team_1_hits": 16343,
        "team_2_hits": 3205,
        "team_1_deaths": 60,
        "team_2_deaths": 165,
        "team_1_wins": 89,
        "team_2_wins": 0,
        "scenarios_run": [
            {
                "scenario_name": "ex_adv_four_corners_pt1",
                "randseed": 0,
                "eval_time": 4.509885400068015,
                "team_1_hits": 36,
                "team_2_hits": 22,
                "team_1_wins": 1,
                "team_2_wins": 0,
                "team_1_deaths": 0,
                "team_2_deaths": 0
            },
            {
                "scenario_name": "ex_adv_asteroids_down_up_pt1",
                "randseed": 0,
                "eval_time": 0.9959840001538396,
                "team_1_hits": 5,
                "team_2_hits": 3,
                "team_1_wins": 1,
                "team_2_wins": 0,
                "team_1_deaths": 0,
                "team_2_deaths": 0
            },
            {
                "scenario_name": "ex_adv_asteroids_down_up_pt2",
                "randseed": 0,
                "eval_time": 0.783659600187093,
                "team_1_hits": 6,
                "team_2_hits": 2,
                "team_1_wins": 1,
                "team_2_wins": 0,
                "team_1_deaths": 0,
                "team_2_deaths": 0
            },
            {
                "scenario_name": "ex_adv_direct_facing",
                "randseed": 0,
                "eval_time": 0.4916470004245639,
                "team_1_hits": 4,
                "team_2_hits": 0,
                "team_1_wins": 1,
                "team_2_wins": 0,
                "team_1_deaths": 0,
                "team_2_deaths": 0
            },
            {
                "scenario_name": "ex_adv_two_asteroids_pt1",
                "randseed": 0,
                "eval_time": 2.1579391001723707,
                "team_1_hits": 18,
                "team_2_hits": 8,
                "team_1_wins": 1,
                "team_2_wins": 0,
                "team_1_deaths": 0,
                "team_2_deaths": 0
            },
            {
                "scenario_name": "ex_adv_two_asteroids_pt2",
                "randseed": 0,
                "eval_time": 1.905399200040847,
                "team_1_hits": 21,
                "team_2_hits": 5,
                "team_1_wins": 1,
                "team_2_wins": 0,
                "team_1_deaths": 0,
                "team_2_deaths": 1
            },
            {
                "scenario_name": "ex_adv_ring_pt1",
                "randseed": 0,
                "eval_time": 1.7252688999287784,
                "team_1_hits": 18,
                "team_2_hits": 1,
                "team_1_wins": 1,
                "team_2_wins": 0,
                "team_1_deaths": 0,
                "team_2_deaths": 0
            },
            {
                "scenario_name": "adv_random_big_1",
                "randseed": 0,
                "eval_time": 56.888505400158465,
                "team_1_hits": 174,
                "team_2_hits": 105,
                "team_1_wins": 1,
                "team_2_wins": 0,
                "team_1_deaths": 0,
                "team_2_deaths": 0
            },
            {
                "scenario_name": "adv_random_big_2",
                "randseed": 0,
                "eval_time": 58.12753069959581,
                "team_1_hits": 175,
                "team_2_hits": 104,
                "team_1_wins": 1,
                "team_2_wins": 0,
                "team_1_deaths": 0,
                "team_2_deaths": 0
            },
            {
                "scenario_name": "adv_random_big_3",
                "randseed": 0,
                "eval_time": 56.44053109968081,
                "team_1_hits": 261,
                "team_2_hits": 41,
                "team_1_wins": 1,
                "team_2_wins": 0,
                "team_1_deaths": 0,
                "team_2_deaths": 3
            },
            {
                "scenario_name": "adv_random_big_4",
                "randseed": 0,
                "eval_time": 59.86034690029919,
                "team_1_hits": 263,
                "team_2_hits": 31,
                "team_1_wins": 1,
                "team_2_wins": 0,
                "team_1_deaths": 0,
                "team_2_deaths": 3
            },
            {
                "scenario_name": "adv_multi_wall_bottom_hard_1",
                "randseed": 0,
                "eval_time": 54.32756160013378,
                "team_1_hits": 238,
                "team_2_hits": 47,
                "team_1_wins": 1,
                "team_2_wins": 0,
                "team_1_deaths": 1,
                "team_2_deaths": 3
            },
            {
                "scenario_name": "adv_multi_wall_right_hard_1",
                "randseed": 0,
                "eval_time": 16.3068019002676,
                "team_1_hits": 26,
                "team_2_hits": 24,
                "team_1_wins": 1,
                "team_2_wins": 0,
                "team_1_deaths": 3,
                "team_2_deaths": 3
            },
            {
                "scenario_name": "adv_multi_ring_closing_left",
                "randseed": 0,
                "eval_time": 217.7754963999614,
                "team_1_hits": 459,
                "team_2_hits": 181,
                "team_1_wins": 1,
                "team_2_wins": 0,
                "team_1_deaths": 1,
                "team_2_deaths": 2
            },
            {
                "scenario_name": "adv_multi_ring_closing_right",
                "randseed": 0,
                "eval_time": 178.53005960024893,
                "team_1_hits": 531,
                "team_2_hits": 109,
                "team_1_wins": 1,
                "team_2_wins": 0,
                "team_1_deaths": 0,
                "team_2_deaths": 3
            },
            {
                "scenario_name": "adv_multi_two_rings_closing",
                "randseed": 0,
                "eval_time": 275.838529500179,
                "team_1_hits": 392,
                "team_2_hits": 29,
                "team_1_wins": 1,
                "team_2_wins": 0,
                "team_1_deaths": 3,
                "team_2_deaths": 3
            },
            {
                "scenario_name": "avg_multi_ring_closing_both2",
                "randseed": 0,
                "eval_time": 33.82506589964032,
                "team_1_hits": 150,
                "team_2_hits": 42,
                "team_1_wins": 1,
                "team_2_wins": 0,
                "team_1_deaths": 0,
                "team_2_deaths": 1
            },
            {
                "scenario_name": "adv_multi_ring_closing_both_inside",
                "randseed": 0,
                "eval_time": 148.48874039994553,
                "team_1_hits": 460,
                "team_2_hits": 49,
                "team_1_wins": 1,
                "team_2_wins": 0,
                "team_1_deaths": 1,
                "team_2_deaths": 3
            },
            {
                "scenario_name": "adv_multi_ring_closing_both_inside_fast",
                "randseed": 0,
                "eval_time": 19.108637900091708,
                "team_1_hits": 98,
                "team_2_hits": 6,
                "team_1_wins": 1,
                "team_2_wins": 0,
                "team_1_deaths": 1,
                "team_2_deaths": 3
            },
            {
                "scenario_name": "Random Scenario 5",
                "randseed": 0,
                "eval_time": 13.551678699906915,
                "team_1_hits": 81,
                "team_2_hits": 20,
                "team_1_wins": 1,
                "team_2_wins": 0,
                "team_1_deaths": 0,
                "team_2_deaths": 2
            },
            {
                "scenario_name": "Random Scenario 6",
                "randseed": 0,
                "eval_time": 28.168456099927425,
                "team_1_hits": 121,
                "team_2_hits": 41,
                "team_1_wins": 1,
                "team_2_wins": 0,
                "team_1_deaths": 0,
                "team_2_deaths": 1
            },
            {
                "scenario_name": "Random Scenario 7",
                "randseed": 0,
                "eval_time": 7.259541899897158,
                "team_1_hits": 43,
                "team_2_hits": 24,
                "team_1_wins": 1,
                "team_2_wins": 0,
                "team_1_deaths": 0,
                "team_2_deaths": 0
            },
            {
                "scenario_name": "Random Scenario 8",
                "randseed": 0,
                "eval_time": 12.973745800089091,
                "team_1_hits": 98,
                "team_2_hits": 45,
                "team_1_wins": 1,
                "team_2_wins": 0,
                "team_1_deaths": 0,
                "team_2_deaths": 1
            },
            {
                "scenario_name": "Random Scenario 9",
                "randseed": 0,
                "eval_time": 6.050042300019413,
                "team_1_hits": 40,
                "team_2_hits": 23,
                "team_1_wins": 1,
                "team_2_wins": 0,
                "team_1_deaths": 0,
                "team_2_deaths": 0
            },
            {
                "scenario_name": "Random Scenario 10",
                "randseed": 0,
                "eval_time": 13.900900200009346,
                "team_1_hits": 69,
                "team_2_hits": 46,
                "team_1_wins": 1,
                "team_2_wins": 0,
                "team_1_deaths": 0,
                "team_2_deaths": 0
            },
            {
                "scenario_name": "Random Scenario 11",
                "randseed": 0,
                "eval_time": 10.350498999934644,
                "team_1_hits": 71,
                "team_2_hits": 24,
                "team_1_wins": 1,
                "team_2_wins": 0,
                "team_1_deaths": 0,
                "team_2_deaths": 1
            },
            {
                "scenario_name": "Random Scenario 12",
                "randseed": 0,
                "eval_time": 21.063987500034273,
                "team_1_hits": 187,
                "team_2_hits": 11,
                "team_1_wins": 1,
                "team_2_wins": 0,
                "team_1_deaths": 0,
                "team_2_deaths": 3
            },
            {
                "scenario_name": "Random Scenario 13",
                "randseed": 0,
                "eval_time": 47.249738599639386,
                "team_1_hits": 193,
                "team_2_hits": 30,
                "team_1_wins": 1,
                "team_2_wins": 0,
                "team_1_deaths": 1,
                "team_2_deaths": 3
            },
            {
                "scenario_name": "Random Scenario 14",
                "randseed": 0,
                "eval_time": 16.877184899989516,
                "team_1_hits": 105,
                "team_2_hits": 23,
                "team_1_wins": 1,
                "team_2_wins": 0,
                "team_1_deaths": 1,
                "team_2_deaths": 3
            },
            {
                "scenario_name": "Random Scenario 15",
                "randseed": 0,
                "eval_time": 27.37300179991871,
                "team_1_hits": 191,
                "team_2_hits": 13,
                "team_1_wins": 1,
                "team_2_wins": 0,
                "team_1_deaths": 1,
                "team_2_deaths": 3
            },
            {
                "scenario_name": "Random Scenario 16",
                "randseed": 0,
                "eval_time": 16.389005200006068,
                "team_1_hits": 98,
                "team_2_hits": 53,
                "team_1_wins": 1,
                "team_2_wins": 0,
                "team_1_deaths": 0,
                "team_2_deaths": 0
            },
            {
                "scenario_name": "Random Scenario 17",
                "randseed": 0,
                "eval_time": 28.517742599826306,
                "team_1_hits": 151,
                "team_2_hits": 46,
                "team_1_wins": 1,
                "team_2_wins": 0,
                "team_1_deaths": 0,
                "team_2_deaths": 2
            },
            {
                "scenario_name": "Random Scenario 18",
                "randseed": 0,
                "eval_time": 67.93585169967264,
                "team_1_hits": 304,
                "team_2_hits": 26,
                "team_1_wins": 1,
                "team_2_wins": 0,
                "team_1_deaths": 0,
                "team_2_deaths": 3
            },
            {
                "scenario_name": "Random Scenario 19",
                "randseed": 0,
                "eval_time": 49.158289100043476,
                "team_1_hits": 337,
                "team_2_hits": 24,
                "team_1_wins": 1,
                "team_2_wins": 0,
                "team_1_deaths": 0,
                "team_2_deaths": 3
            },
            {
                "scenario_name": "Random Scenario 20",
                "randseed": 0,
                "eval_time": 48.080428400076926,
                "team_1_hits": 277,
                "team_2_hits": 25,
                "team_1_wins": 1,
                "team_2_wins": 0,
                "team_1_deaths": 0,
                "team_2_deaths": 3
            },
            {
                "scenario_name": "Random Scenario 21",
                "randseed": 0,
                "eval_time": 39.950220400001854,
                "team_1_hits": 165,
                "team_2_hits": 84,
                "team_1_wins": 1,
                "team_2_wins": 0,
                "team_1_deaths": 1,
                "team_2_deaths": 2
            },
            {
                "scenario_name": "Random Scenario 22",
                "randseed": 0,
                "eval_time": 51.69946580007672,
                "team_1_hits": 302,
                "team_2_hits": 11,
                "team_1_wins": 1,
                "team_2_wins": 0,
                "team_1_deaths": 0,
                "team_2_deaths": 3
            },
            {
                "scenario_name": "Random Scenario 23",
                "randseed": 0,
                "eval_time": 87.50385450012982,
                "team_1_hits": 196,
                "team_2_hits": 15,
                "team_1_wins": 1,
                "team_2_wins": 0,
                "team_1_deaths": 3,
                "team_2_deaths": 3
            },
            {
                "scenario_name": "Random Scenario 24",
                "randseed": 0,
                "eval_time": 33.077626099810004,
                "team_1_hits": 67,
                "team_2_hits": 13,
                "team_1_wins": 1,
                "team_2_wins": 0,
                "team_1_deaths": 3,
                "team_2_deaths": 3
            },
            {
                "scenario_name": "Random Scenario 25",
                "randseed": 0,
                "eval_time": 87.5499837002717,
                "team_1_hits": 313,
                "team_2_hits": 12,
                "team_1_wins": 1,
                "team_2_wins": 0,
                "team_1_deaths": 2,
                "team_2_deaths": 3
            },
            {
                "scenario_name": "Random Scenario 26",
                "randseed": 0,
                "eval_time": 44.63283669995144,
                "team_1_hits": 339,
                "team_2_hits": 14,
                "team_1_wins": 1,
                "team_2_wins": 0,
                "team_1_deaths": 1,
                "team_2_deaths": 3
            },
            {
                "scenario_name": "Random Scenario 27",
                "randseed": 0,
                "eval_time": 69.5673623001203,
                "team_1_hits": 367,
                "team_2_hits": 29,
                "team_1_wins": 1,
                "team_2_wins": 0,
                "team_1_deaths": 0,
                "team_2_deaths": 3
            },
            {
                "scenario_name": "Random Scenario 28",
                "randseed": 0,
                "eval_time": 47.33873589988798,
                "team_1_hits": 119,
                "team_2_hits": 14,
                "team_1_wins": 1,
                "team_2_wins": 0,
                "team_1_deaths": 3,
                "team_2_deaths": 3
            },
            {
                "scenario_name": "Random Scenario 29",
                "randseed": 0,
                "eval_time": 56.17463140003383,
                "team_1_hits": 342,
                "team_2_hits": 20,
                "team_1_wins": 1,
                "team_2_wins": 0,
                "team_1_deaths": 0,
                "team_2_deaths": 3
            },
            {
                "scenario_name": "Random Scenario 30",
                "randseed": 0,
                "eval_time": 76.61883510043845,
                "team_1_hits": 173,
                "team_2_hits": 13,
                "team_1_wins": 1,
                "team_2_wins": 0,
                "team_1_deaths": 3,
                "team_2_deaths": 3
            },
            {
                "scenario_name": "ex_adv_four_corners_pt1",
                "randseed": 1,
                "eval_time": 6.0704870000481606,
                "team_1_hits": 39,
                "team_2_hits": 19,
                "team_1_wins": 1,
                "team_2_wins": 0,
                "team_1_deaths": 0,
                "team_2_deaths": 0
            },
            {
                "scenario_name": "ex_adv_asteroids_down_up_pt1",
                "randseed": 1,
                "eval_time": 1.2619435000233352,
                "team_1_hits": 5,
                "team_2_hits": 3,
                "team_1_wins": 1,
                "team_2_wins": 0,
                "team_1_deaths": 0,
                "team_2_deaths": 0
            },
            {
                "scenario_name": "ex_adv_asteroids_down_up_pt2",
                "randseed": 1,
                "eval_time": 1.3633668003603816,
                "team_1_hits": 6,
                "team_2_hits": 2,
                "team_1_wins": 1,
                "team_2_wins": 0,
                "team_1_deaths": 0,
                "team_2_deaths": 0
            },
            {
                "scenario_name": "ex_adv_direct_facing",
                "randseed": 1,
                "eval_time": 0.669749699998647,
                "team_1_hits": 4,
                "team_2_hits": 0,
                "team_1_wins": 1,
                "team_2_wins": 0,
                "team_1_deaths": 0,
                "team_2_deaths": 0
            },
            {
                "scenario_name": "ex_adv_two_asteroids_pt1",
                "randseed": 1,
                "eval_time": 2.680949500296265,
                "team_1_hits": 18,
                "team_2_hits": 8,
                "team_1_wins": 1,
                "team_2_wins": 0,
                "team_1_deaths": 0,
                "team_2_deaths": 0
            },
            {
                "scenario_name": "ex_adv_two_asteroids_pt2",
                "randseed": 1,
                "eval_time": 3.582557999994606,
                "team_1_hits": 16,
                "team_2_hits": 10,
                "team_1_wins": 1,
                "team_2_wins": 0,
                "team_1_deaths": 0,
                "team_2_deaths": 1
            },
            {
                "scenario_name": "ex_adv_ring_pt1",
                "randseed": 1,
                "eval_time": 2.2173611000180244,
                "team_1_hits": 18,
                "team_2_hits": 1,
                "team_1_wins": 1,
                "team_2_wins": 0,
                "team_1_deaths": 0,
                "team_2_deaths": 0
            },
            {
                "scenario_name": "adv_random_big_1",
                "randseed": 1,
                "eval_time": 57.492893599905074,
                "team_1_hits": 184,
                "team_2_hits": 95,
                "team_1_wins": 1,
                "team_2_wins": 0,
                "team_1_deaths": 0,
                "team_2_deaths": 0
            },
            {
                "scenario_name": "adv_random_big_2",
                "randseed": 1,
                "eval_time": 45.20044280029833,
                "team_1_hits": 164,
                "team_2_hits": 115,
                "team_1_wins": 1,
                "team_2_wins": 0,
                "team_1_deaths": 0,
                "team_2_deaths": 0
            },
            {
                "scenario_name": "adv_random_big_3",
                "randseed": 1,
                "eval_time": 49.331600999925286,
                "team_1_hits": 251,
                "team_2_hits": 27,
                "team_1_wins": 1,
                "team_2_wins": 0,
                "team_1_deaths": 0,
                "team_2_deaths": 3
            },
            {
                "scenario_name": "adv_random_big_4",
                "randseed": 1,
                "eval_time": 47.294581099879,
                "team_1_hits": 255,
                "team_2_hits": 38,
                "team_1_wins": 1,
                "team_2_wins": 0,
                "team_1_deaths": 0,
                "team_2_deaths": 3
            },
            {
                "scenario_name": "adv_multi_wall_bottom_hard_1",
                "randseed": 1,
                "eval_time": 61.21189989987761,
                "team_1_hits": 249,
                "team_2_hits": 72,
                "team_1_wins": 1,
                "team_2_wins": 0,
                "team_1_deaths": 1,
                "team_2_deaths": 3
            },
            {
                "scenario_name": "adv_multi_wall_right_hard_1",
                "randseed": 1,
                "eval_time": 67.64556220034137,
                "team_1_hits": 237,
                "team_2_hits": 19,
                "team_1_wins": 1,
                "team_2_wins": 0,
                "team_1_deaths": 1,
                "team_2_deaths": 3
            },
            {
                "scenario_name": "adv_multi_ring_closing_left",
                "randseed": 1,
                "eval_time": 300.5358381001279,
                "team_1_hits": 552,
                "team_2_hits": 88,
                "team_1_wins": 1,
                "team_2_wins": 0,
                "team_1_deaths": 2,
                "team_2_deaths": 3
            },
            {
                "scenario_name": "adv_multi_ring_closing_right",
                "randseed": 1,
                "eval_time": 175.7108543999493,
                "team_1_hits": 404,
                "team_2_hits": 236,
                "team_1_wins": 1,
                "team_2_wins": 0,
                "team_1_deaths": 0,
                "team_2_deaths": 1
            },
            {
                "scenario_name": "adv_multi_two_rings_closing",
                "randseed": 1,
                "eval_time": 159.27743630018085,
                "team_1_hits": 254,
                "team_2_hits": 31,
                "team_1_wins": 1,
                "team_2_wins": 0,
                "team_1_deaths": 3,
                "team_2_deaths": 3
            },
            {
                "scenario_name": "avg_multi_ring_closing_both2",
                "randseed": 1,
                "eval_time": 38.200808299705386,
                "team_1_hits": 96,
                "team_2_hits": 96,
                "team_1_wins": 0,
                "team_2_wins": 0,
                "team_1_deaths": 3,
                "team_2_deaths": 1
            },
            {
                "scenario_name": "adv_multi_ring_closing_both_inside",
                "randseed": 1,
                "eval_time": 216.7606943999417,
                "team_1_hits": 463,
                "team_2_hits": 92,
                "team_1_wins": 1,
                "team_2_wins": 0,
                "team_1_deaths": 1,
                "team_2_deaths": 3
            },
            {
                "scenario_name": "adv_multi_ring_closing_both_inside_fast",
                "randseed": 1,
                "eval_time": 19.00222170026973,
                "team_1_hits": 97,
                "team_2_hits": 7,
                "team_1_wins": 1,
                "team_2_wins": 0,
                "team_1_deaths": 1,
                "team_2_deaths": 3
            },
            {
                "scenario_name": "Random Scenario 5",
                "randseed": 1,
                "eval_time": 13.50982980011031,
                "team_1_hits": 80,
                "team_2_hits": 21,
                "team_1_wins": 1,
                "team_2_wins": 0,
                "team_1_deaths": 0,
                "team_2_deaths": 0
            },
            {
                "scenario_name": "Random Scenario 6",
                "randseed": 1,
                "eval_time": 31.463652800302953,
                "team_1_hits": 121,
                "team_2_hits": 41,
                "team_1_wins": 1,
                "team_2_wins": 0,
                "team_1_deaths": 0,
                "team_2_deaths": 2
            },
            {
                "scenario_name": "Random Scenario 7",
                "randseed": 1,
                "eval_time": 7.046089600306004,
                "team_1_hits": 43,
                "team_2_hits": 24,
                "team_1_wins": 1,
                "team_2_wins": 0,
                "team_1_deaths": 0,
                "team_2_deaths": 0
            },
            {
                "scenario_name": "Random Scenario 8",
                "randseed": 1,
                "eval_time": 14.97962629981339,
                "team_1_hits": 101,
                "team_2_hits": 42,
                "team_1_wins": 1,
                "team_2_wins": 0,
                "team_1_deaths": 0,
                "team_2_deaths": 1
            },
            {
                "scenario_name": "Random Scenario 9",
                "randseed": 1,
                "eval_time": 5.745809199754149,
                "team_1_hits": 41,
                "team_2_hits": 22,
                "team_1_wins": 1,
                "team_2_wins": 0,
                "team_1_deaths": 0,
                "team_2_deaths": 0
            },
            {
                "scenario_name": "Random Scenario 10",
                "randseed": 1,
                "eval_time": 14.683320799842477,
                "team_1_hits": 66,
                "team_2_hits": 49,
                "team_1_wins": 1,
                "team_2_wins": 0,
                "team_1_deaths": 0,
                "team_2_deaths": 0
            },
            {
                "scenario_name": "Random Scenario 11",
                "randseed": 1,
                "eval_time": 12.289348599966615,
                "team_1_hits": 78,
                "team_2_hits": 17,
                "team_1_wins": 1,
                "team_2_wins": 0,
                "team_1_deaths": 0,
                "team_2_deaths": 2
            },
            {
                "scenario_name": "Random Scenario 12",
                "randseed": 1,
                "eval_time": 30.794011800084263,
                "team_1_hits": 166,
                "team_2_hits": 32,
                "team_1_wins": 1,
                "team_2_wins": 0,
                "team_1_deaths": 0,
                "team_2_deaths": 2
            },
            {
                "scenario_name": "Random Scenario 13",
                "randseed": 1,
                "eval_time": 34.75450700009242,
                "team_1_hits": 210,
                "team_2_hits": 13,
                "team_1_wins": 1,
                "team_2_wins": 0,
                "team_1_deaths": 0,
                "team_2_deaths": 3
            },
            {
                "scenario_name": "Random Scenario 14",
                "randseed": 1,
                "eval_time": 23.48815710004419,
                "team_1_hits": 96,
                "team_2_hits": 32,
                "team_1_wins": 1,
                "team_2_wins": 0,
                "team_1_deaths": 2,
                "team_2_deaths": 1
            },
            {
                "scenario_name": "Random Scenario 15",
                "randseed": 1,
                "eval_time": 30.26572490017861,
                "team_1_hits": 181,
                "team_2_hits": 23,
                "team_1_wins": 1,
                "team_2_wins": 0,
                "team_1_deaths": 1,
                "team_2_deaths": 3
            },
            {
                "scenario_name": "Random Scenario 16",
                "randseed": 1,
                "eval_time": 17.605733399745077,
                "team_1_hits": 93,
                "team_2_hits": 58,
                "team_1_wins": 1,
                "team_2_wins": 0,
                "team_1_deaths": 0,
                "team_2_deaths": 0
            },
            {
                "scenario_name": "Random Scenario 17",
                "randseed": 1,
                "eval_time": 29.240374700166285,
                "team_1_hits": 147,
                "team_2_hits": 50,
                "team_1_wins": 1,
                "team_2_wins": 0,
                "team_1_deaths": 0,
                "team_2_deaths": 2
            },
            {
                "scenario_name": "Random Scenario 18",
                "randseed": 1,
                "eval_time": 66.20318699954078,
                "team_1_hits": 310,
                "team_2_hits": 20,
                "team_1_wins": 1,
                "team_2_wins": 0,
                "team_1_deaths": 1,
                "team_2_deaths": 3
            },
            {
                "scenario_name": "Random Scenario 19",
                "randseed": 1,
                "eval_time": 58.16780410008505,
                "team_1_hits": 339,
                "team_2_hits": 22,
                "team_1_wins": 1,
                "team_2_wins": 0,
                "team_1_deaths": 0,
                "team_2_deaths": 3
            },
            {
                "scenario_name": "Random Scenario 20",
                "randseed": 1,
                "eval_time": 82.82881110021845,
                "team_1_hits": 284,
                "team_2_hits": 18,
                "team_1_wins": 1,
                "team_2_wins": 0,
                "team_1_deaths": 2,
                "team_2_deaths": 3
            },
            {
                "scenario_name": "Random Scenario 21",
                "randseed": 1,
                "eval_time": 41.94725369988009,
                "team_1_hits": 156,
                "team_2_hits": 93,
                "team_1_wins": 1,
                "team_2_wins": 0,
                "team_1_deaths": 1,
                "team_2_deaths": 1
            },
            {
                "scenario_name": "Random Scenario 22",
                "randseed": 1,
                "eval_time": 38.31457790033892,
                "team_1_hits": 305,
                "team_2_hits": 8,
                "team_1_wins": 1,
                "team_2_wins": 0,
                "team_1_deaths": 0,
                "team_2_deaths": 3
            },
            {
                "scenario_name": "Random Scenario 23",
                "randseed": 1,
                "eval_time": 102.943565600086,
                "team_1_hits": 466,
                "team_2_hits": 34,
                "team_1_wins": 1,
                "team_2_wins": 0,
                "team_1_deaths": 0,
                "team_2_deaths": 3
            },
            {
                "scenario_name": "Random Scenario 24",
                "randseed": 1,
                "eval_time": 16.69953169999644,
                "team_1_hits": 36,
                "team_2_hits": 20,
                "team_1_wins": 1,
                "team_2_wins": 0,
                "team_1_deaths": 3,
                "team_2_deaths": 3
            },
            {
                "scenario_name": "Random Scenario 25",
                "randseed": 1,
                "eval_time": 52.56263429997489,
                "team_1_hits": 316,
                "team_2_hits": 9,
                "team_1_wins": 1,
                "team_2_wins": 0,
                "team_1_deaths": 1,
                "team_2_deaths": 3
            },
            {
                "scenario_name": "Random Scenario 26",
                "randseed": 1,
                "eval_time": 65.1003095000051,
                "team_1_hits": 336,
                "team_2_hits": 17,
                "team_1_wins": 1,
                "team_2_wins": 0,
                "team_1_deaths": 1,
                "team_2_deaths": 3
            },
            {
                "scenario_name": "Random Scenario 27",
                "randseed": 1,
                "eval_time": 62.927056999877095,
                "team_1_hits": 377,
                "team_2_hits": 19,
                "team_1_wins": 1,
                "team_2_wins": 0,
                "team_1_deaths": 1,
                "team_2_deaths": 3
            },
            {
                "scenario_name": "Random Scenario 28",
                "randseed": 1,
                "eval_time": 35.57899670023471,
                "team_1_hits": 97,
                "team_2_hits": 22,
                "team_1_wins": 1,
                "team_2_wins": 0,
                "team_1_deaths": 3,
                "team_2_deaths": 3
            },
            {
                "scenario_name": "Random Scenario 29",
                "randseed": 1,
                "eval_time": 48.11132859997451,
                "team_1_hits": 342,
                "team_2_hits": 20,
                "team_1_wins": 1,
                "team_2_wins": 0,
                "team_1_deaths": 0,
                "team_2_deaths": 3
            },
            {
                "scenario_name": "Random Scenario 30",
                "randseed": 1,
                "eval_time": 63.78522050008178,
                "team_1_hits": 160,
                "team_2_hits": 12,
                "team_1_wins": 1,
                "team_2_wins": 0,
                "team_1_deaths": 3,
                "team_2_deaths": 3
            }
        ]
    }
]