[
    {
        "timestamp": "2024-02-19T17:12:59.417832",
        "total_eval_time": 4475.362552700099,
        "chromosome": [
            1.4903928828920305,
            1.2708137124900027,
            0.14281659594456264,
            0.5771092904932665,
            1.1255379327938528,
            1.4848443402937135,
            0.9084852450925711
        ],
        "team_1_hits": 16346,
        "team_2_hits": 3202,
        "team_1_deaths": 60,
        "team_2_deaths": 165,
        "team_1_wins": 89,
        "team_2_wins": 0,
        "scenarios_run": [
            {
                "scenario_name": "ex_adv_four_corners_pt1",
                "randseed": 0,
                "eval_time": 3.853039899840951,
                "team_1_hits": 39,
                "team_2_hits": 19,
                "team_1_wins": 1,
                "team_2_wins": 0,
                "team_1_deaths": 0,
                "team_2_deaths": 0
            },
            {
                "scenario_name": "ex_adv_asteroids_down_up_pt1",
                "randseed": 0,
                "eval_time": 0.7662623999640346,
                "team_1_hits": 5,
                "team_2_hits": 3,
                "team_1_wins": 1,
                "team_2_wins": 0,
                "team_1_deaths": 0,
                "team_2_deaths": 0
            },
            {
                "scenario_name": "ex_adv_asteroids_down_up_pt2",
                "randseed": 0,
                "eval_time": 0.7709812996909022,
                "team_1_hits": 6,
                "team_2_hits": 2,
                "team_1_wins": 1,
                "team_2_wins": 0,
                "team_1_deaths": 0,
                "team_2_deaths": 0
            },
            {
                "scenario_name": "ex_adv_direct_facing",
                "randseed": 0,
                "eval_time": 0.44216949958354235,
                "team_1_hits": 4,
                "team_2_hits": 0,
                "team_1_wins": 1,
                "team_2_wins": 0,
                "team_1_deaths": 0,
                "team_2_deaths": 0
            },
            {
                "scenario_name": "ex_adv_two_asteroids_pt1",
                "randseed": 0,
                "eval_time": 1.8431746000424027,
                "team_1_hits": 18,
                "team_2_hits": 8,
                "team_1_wins": 1,
                "team_2_wins": 0,
                "team_1_deaths": 0,
                "team_2_deaths": 0
            },
            {
                "scenario_name": "ex_adv_two_asteroids_pt2",
                "randseed": 0,
                "eval_time": 1.7700388999655843,
                "team_1_hits": 21,
                "team_2_hits": 5,
                "team_1_wins": 1,
                "team_2_wins": 0,
                "team_1_deaths": 0,
                "team_2_deaths": 1
            },
            {
                "scenario_name": "ex_adv_ring_pt1",
                "randseed": 0,
                "eval_time": 1.5634515997953713,
                "team_1_hits": 18,
                "team_2_hits": 1,
                "team_1_wins": 1,
                "team_2_wins": 0,
                "team_1_deaths": 0,
                "team_2_deaths": 0
            },
            {
                "scenario_name": "adv_random_big_1",
                "randseed": 0,
                "eval_time": 55.882947999984026,
                "team_1_hits": 174,
                "team_2_hits": 105,
                "team_1_wins": 1,
                "team_2_wins": 0,
                "team_1_deaths": 0,
                "team_2_deaths": 0
            },
            {
                "scenario_name": "adv_random_big_2",
                "randseed": 0,
                "eval_time": 58.444249500054866,
                "team_1_hits": 175,
                "team_2_hits": 104,
                "team_1_wins": 1,
                "team_2_wins": 0,
                "team_1_deaths": 0,
                "team_2_deaths": 0
            },
            {
                "scenario_name": "adv_random_big_3",
                "randseed": 0,
                "eval_time": 57.617446599993855,
                "team_1_hits": 261,
                "team_2_hits": 41,
                "team_1_wins": 1,
                "team_2_wins": 0,
                "team_1_deaths": 0,
                "team_2_deaths": 3
            },
            {
                "scenario_name": "adv_random_big_4",
                "randseed": 0,
                "eval_time": 60.52751139970496,
                "team_1_hits": 263,
                "team_2_hits": 31,
                "team_1_wins": 1,
                "team_2_wins": 0,
                "team_1_deaths": 0,
                "team_2_deaths": 3
            },
            {
                "scenario_name": "adv_multi_wall_bottom_hard_1",
                "randseed": 0,
                "eval_time": 54.16752089979127,
                "team_1_hits": 238,
                "team_2_hits": 47,
                "team_1_wins": 1,
                "team_2_wins": 0,
                "team_1_deaths": 1,
                "team_2_deaths": 3
            },
            {
                "scenario_name": "adv_multi_wall_right_hard_1",
                "randseed": 0,
                "eval_time": 16.569909000303596,
                "team_1_hits": 26,
                "team_2_hits": 24,
                "team_1_wins": 1,
                "team_2_wins": 0,
                "team_1_deaths": 3,
                "team_2_deaths": 3
            },
            {
                "scenario_name": "adv_multi_ring_closing_left",
                "randseed": 0,
                "eval_time": 218.59234400000423,
                "team_1_hits": 459,
                "team_2_hits": 181,
                "team_1_wins": 1,
                "team_2_wins": 0,
                "team_1_deaths": 1,
                "team_2_deaths": 2
            },
            {
                "scenario_name": "adv_multi_ring_closing_right",
                "randseed": 0,
                "eval_time": 180.12293649977073,
                "team_1_hits": 531,
                "team_2_hits": 109,
                "team_1_wins": 1,
                "team_2_wins": 0,
                "team_1_deaths": 0,
                "team_2_deaths": 3
            },
            {
                "scenario_name": "adv_multi_two_rings_closing",
                "randseed": 0,
                "eval_time": 278.0571971000172,
                "team_1_hits": 392,
                "team_2_hits": 29,
                "team_1_wins": 1,
                "team_2_wins": 0,
                "team_1_deaths": 3,
                "team_2_deaths": 3
            },
            {
                "scenario_name": "avg_multi_ring_closing_both2",
                "randseed": 0,
                "eval_time": 34.06886449968442,
                "team_1_hits": 150,
                "team_2_hits": 42,
                "team_1_wins": 1,
                "team_2_wins": 0,
                "team_1_deaths": 0,
                "team_2_deaths": 1
            },
            {
                "scenario_name": "adv_multi_ring_closing_both_inside",
                "randseed": 0,
                "eval_time": 150.13066600030288,
                "team_1_hits": 460,
                "team_2_hits": 49,
                "team_1_wins": 1,
                "team_2_wins": 0,
                "team_1_deaths": 1,
                "team_2_deaths": 3
            },
            {
                "scenario_name": "adv_multi_ring_closing_both_inside_fast",
                "randseed": 0,
                "eval_time": 19.383394999895245,
                "team_1_hits": 98,
                "team_2_hits": 6,
                "team_1_wins": 1,
                "team_2_wins": 0,
                "team_1_deaths": 1,
                "team_2_deaths": 3
            },
            {
                "scenario_name": "Random Scenario 5",
                "randseed": 0,
                "eval_time": 13.558307799976319,
                "team_1_hits": 81,
                "team_2_hits": 20,
                "team_1_wins": 1,
                "team_2_wins": 0,
                "team_1_deaths": 0,
                "team_2_deaths": 2
            },
            {
                "scenario_name": "Random Scenario 6",
                "randseed": 0,
                "eval_time": 28.183728899806738,
                "team_1_hits": 121,
                "team_2_hits": 41,
                "team_1_wins": 1,
                "team_2_wins": 0,
                "team_1_deaths": 0,
                "team_2_deaths": 1
            },
            {
                "scenario_name": "Random Scenario 7",
                "randseed": 0,
                "eval_time": 7.2657099002972245,
                "team_1_hits": 43,
                "team_2_hits": 24,
                "team_1_wins": 1,
                "team_2_wins": 0,
                "team_1_deaths": 0,
                "team_2_deaths": 0
            },
            {
                "scenario_name": "Random Scenario 8",
                "randseed": 0,
                "eval_time": 13.193703799974173,
                "team_1_hits": 98,
                "team_2_hits": 45,
                "team_1_wins": 1,
                "team_2_wins": 0,
                "team_1_deaths": 0,
                "team_2_deaths": 1
            },
            {
                "scenario_name": "Random Scenario 9",
                "randseed": 0,
                "eval_time": 6.039552400354296,
                "team_1_hits": 40,
                "team_2_hits": 23,
                "team_1_wins": 1,
                "team_2_wins": 0,
                "team_1_deaths": 0,
                "team_2_deaths": 0
            },
            {
                "scenario_name": "Random Scenario 10",
                "randseed": 0,
                "eval_time": 13.998860999941826,
                "team_1_hits": 69,
                "team_2_hits": 46,
                "team_1_wins": 1,
                "team_2_wins": 0,
                "team_1_deaths": 0,
                "team_2_deaths": 0
            },
            {
                "scenario_name": "Random Scenario 11",
                "randseed": 0,
                "eval_time": 10.591875300277025,
                "team_1_hits": 71,
                "team_2_hits": 24,
                "team_1_wins": 1,
                "team_2_wins": 0,
                "team_1_deaths": 0,
                "team_2_deaths": 1
            },
            {
                "scenario_name": "Random Scenario 12",
                "randseed": 0,
                "eval_time": 21.163250599987805,
                "team_1_hits": 187,
                "team_2_hits": 11,
                "team_1_wins": 1,
                "team_2_wins": 0,
                "team_1_deaths": 0,
                "team_2_deaths": 3
            },
            {
                "scenario_name": "Random Scenario 13",
                "randseed": 0,
                "eval_time": 47.675891999620944,
                "team_1_hits": 193,
                "team_2_hits": 30,
                "team_1_wins": 1,
                "team_2_wins": 0,
                "team_1_deaths": 1,
                "team_2_deaths": 3
            },
            {
                "scenario_name": "Random Scenario 14",
                "randseed": 0,
                "eval_time": 17.04029029980302,
                "team_1_hits": 105,
                "team_2_hits": 23,
                "team_1_wins": 1,
                "team_2_wins": 0,
                "team_1_deaths": 1,
                "team_2_deaths": 3
            },
            {
                "scenario_name": "Random Scenario 15",
                "randseed": 0,
                "eval_time": 27.56382740009576,
                "team_1_hits": 191,
                "team_2_hits": 13,
                "team_1_wins": 1,
                "team_2_wins": 0,
                "team_1_deaths": 1,
                "team_2_deaths": 3
            },
            {
                "scenario_name": "Random Scenario 16",
                "randseed": 0,
                "eval_time": 16.632099099922925,
                "team_1_hits": 98,
                "team_2_hits": 53,
                "team_1_wins": 1,
                "team_2_wins": 0,
                "team_1_deaths": 0,
                "team_2_deaths": 0
            },
            {
                "scenario_name": "Random Scenario 17",
                "randseed": 0,
                "eval_time": 28.520460300147533,
                "team_1_hits": 151,
                "team_2_hits": 46,
                "team_1_wins": 1,
                "team_2_wins": 0,
                "team_1_deaths": 0,
                "team_2_deaths": 2
            },
            {
                "scenario_name": "Random Scenario 18",
                "randseed": 0,
                "eval_time": 68.20735189970583,
                "team_1_hits": 304,
                "team_2_hits": 26,
                "team_1_wins": 1,
                "team_2_wins": 0,
                "team_1_deaths": 0,
                "team_2_deaths": 3
            },
            {
                "scenario_name": "Random Scenario 19",
                "randseed": 0,
                "eval_time": 49.64426870038733,
                "team_1_hits": 337,
                "team_2_hits": 24,
                "team_1_wins": 1,
                "team_2_wins": 0,
                "team_1_deaths": 0,
                "team_2_deaths": 3
            },
            {
                "scenario_name": "Random Scenario 20",
                "randseed": 0,
                "eval_time": 48.986331700347364,
                "team_1_hits": 277,
                "team_2_hits": 25,
                "team_1_wins": 1,
                "team_2_wins": 0,
                "team_1_deaths": 0,
                "team_2_deaths": 3
            },
            {
                "scenario_name": "Random Scenario 21",
                "randseed": 0,
                "eval_time": 40.03812859999016,
                "team_1_hits": 165,
                "team_2_hits": 84,
                "team_1_wins": 1,
                "team_2_wins": 0,
                "team_1_deaths": 1,
                "team_2_deaths": 2
            },
            {
                "scenario_name": "Random Scenario 22",
                "randseed": 0,
                "eval_time": 52.123648799955845,
                "team_1_hits": 302,
                "team_2_hits": 11,
                "team_1_wins": 1,
                "team_2_wins": 0,
                "team_1_deaths": 0,
                "team_2_deaths": 3
            },
            {
                "scenario_name": "Random Scenario 23",
                "randseed": 0,
                "eval_time": 87.86297280015424,
                "team_1_hits": 196,
                "team_2_hits": 15,
                "team_1_wins": 1,
                "team_2_wins": 0,
                "team_1_deaths": 3,
                "team_2_deaths": 3
            },
            {
                "scenario_name": "Random Scenario 24",
                "randseed": 0,
                "eval_time": 33.89777990011498,
                "team_1_hits": 67,
                "team_2_hits": 13,
                "team_1_wins": 1,
                "team_2_wins": 0,
                "team_1_deaths": 3,
                "team_2_deaths": 3
            },
            {
                "scenario_name": "Random Scenario 25",
                "randseed": 0,
                "eval_time": 87.73588629998267,
                "team_1_hits": 313,
                "team_2_hits": 12,
                "team_1_wins": 1,
                "team_2_wins": 0,
                "team_1_deaths": 2,
                "team_2_deaths": 3
            },
            {
                "scenario_name": "Random Scenario 26",
                "randseed": 0,
                "eval_time": 44.9383089998737,
                "team_1_hits": 339,
                "team_2_hits": 14,
                "team_1_wins": 1,
                "team_2_wins": 0,
                "team_1_deaths": 1,
                "team_2_deaths": 3
            },
            {
                "scenario_name": "Random Scenario 27",
                "randseed": 0,
                "eval_time": 69.917765900027,
                "team_1_hits": 367,
                "team_2_hits": 29,
                "team_1_wins": 1,
                "team_2_wins": 0,
                "team_1_deaths": 0,
                "team_2_deaths": 3
            },
            {
                "scenario_name": "Random Scenario 28",
                "randseed": 0,
                "eval_time": 47.668662399984896,
                "team_1_hits": 119,
                "team_2_hits": 14,
                "team_1_wins": 1,
                "team_2_wins": 0,
                "team_1_deaths": 3,
                "team_2_deaths": 3
            },
            {
                "scenario_name": "Random Scenario 29",
                "randseed": 0,
                "eval_time": 57.265741399955004,
                "team_1_hits": 342,
                "team_2_hits": 20,
                "team_1_wins": 1,
                "team_2_wins": 0,
                "team_1_deaths": 0,
                "team_2_deaths": 3
            },
            {
                "scenario_name": "Random Scenario 30",
                "randseed": 0,
                "eval_time": 78.15245229983702,
                "team_1_hits": 173,
                "team_2_hits": 13,
                "team_1_wins": 1,
                "team_2_wins": 0,
                "team_1_deaths": 3,
                "team_2_deaths": 3
            },
            {
                "scenario_name": "ex_adv_four_corners_pt1",
                "randseed": 1,
                "eval_time": 6.4146332000382245,
                "team_1_hits": 39,
                "team_2_hits": 19,
                "team_1_wins": 1,
                "team_2_wins": 0,
                "team_1_deaths": 0,
                "team_2_deaths": 0
            },
            {
                "scenario_name": "ex_adv_asteroids_down_up_pt1",
                "randseed": 1,
                "eval_time": 1.3091985997743905,
                "team_1_hits": 5,
                "team_2_hits": 3,
                "team_1_wins": 1,
                "team_2_wins": 0,
                "team_1_deaths": 0,
                "team_2_deaths": 0
            },
            {
                "scenario_name": "ex_adv_asteroids_down_up_pt2",
                "randseed": 1,
                "eval_time": 1.3297930001281202,
                "team_1_hits": 6,
                "team_2_hits": 2,
                "team_1_wins": 1,
                "team_2_wins": 0,
                "team_1_deaths": 0,
                "team_2_deaths": 0
            },
            {
                "scenario_name": "ex_adv_direct_facing",
                "randseed": 1,
                "eval_time": 0.7472536000423133,
                "team_1_hits": 4,
                "team_2_hits": 0,
                "team_1_wins": 1,
                "team_2_wins": 0,
                "team_1_deaths": 0,
                "team_2_deaths": 0
            },
            {
                "scenario_name": "ex_adv_two_asteroids_pt1",
                "randseed": 1,
                "eval_time": 2.4784264997579157,
                "team_1_hits": 18,
                "team_2_hits": 8,
                "team_1_wins": 1,
                "team_2_wins": 0,
                "team_1_deaths": 0,
                "team_2_deaths": 0
            },
            {
                "scenario_name": "ex_adv_two_asteroids_pt2",
                "randseed": 1,
                "eval_time": 3.1452112002298236,
                "team_1_hits": 16,
                "team_2_hits": 10,
                "team_1_wins": 1,
                "team_2_wins": 0,
                "team_1_deaths": 0,
                "team_2_deaths": 1
            },
            {
                "scenario_name": "ex_adv_ring_pt1",
                "randseed": 1,
                "eval_time": 2.0582998995669186,
                "team_1_hits": 18,
                "team_2_hits": 1,
                "team_1_wins": 1,
                "team_2_wins": 0,
                "team_1_deaths": 0,
                "team_2_deaths": 0
            },
            {
                "scenario_name": "adv_random_big_1",
                "randseed": 1,
                "eval_time": 57.38277589995414,
                "team_1_hits": 184,
                "team_2_hits": 95,
                "team_1_wins": 1,
                "team_2_wins": 0,
                "team_1_deaths": 0,
                "team_2_deaths": 0
            },
            {
                "scenario_name": "adv_random_big_2",
                "randseed": 1,
                "eval_time": 45.278727600350976,
                "team_1_hits": 164,
                "team_2_hits": 115,
                "team_1_wins": 1,
                "team_2_wins": 0,
                "team_1_deaths": 0,
                "team_2_deaths": 0
            },
            {
                "scenario_name": "adv_random_big_3",
                "randseed": 1,
                "eval_time": 49.44897919986397,
                "team_1_hits": 251,
                "team_2_hits": 27,
                "team_1_wins": 1,
                "team_2_wins": 0,
                "team_1_deaths": 0,
                "team_2_deaths": 3
            },
            {
                "scenario_name": "adv_random_big_4",
                "randseed": 1,
                "eval_time": 47.24507590010762,
                "team_1_hits": 255,
                "team_2_hits": 38,
                "team_1_wins": 1,
                "team_2_wins": 0,
                "team_1_deaths": 0,
                "team_2_deaths": 3
            },
            {
                "scenario_name": "adv_multi_wall_bottom_hard_1",
                "randseed": 1,
                "eval_time": 61.94171189982444,
                "team_1_hits": 249,
                "team_2_hits": 72,
                "team_1_wins": 1,
                "team_2_wins": 0,
                "team_1_deaths": 1,
                "team_2_deaths": 3
            },
            {
                "scenario_name": "adv_multi_wall_right_hard_1",
                "randseed": 1,
                "eval_time": 67.91881360020489,
                "team_1_hits": 237,
                "team_2_hits": 19,
                "team_1_wins": 1,
                "team_2_wins": 0,
                "team_1_deaths": 1,
                "team_2_deaths": 3
            },
            {
                "scenario_name": "adv_multi_ring_closing_left",
                "randseed": 1,
                "eval_time": 302.0605071000755,
                "team_1_hits": 552,
                "team_2_hits": 88,
                "team_1_wins": 1,
                "team_2_wins": 0,
                "team_1_deaths": 2,
                "team_2_deaths": 3
            },
            {
                "scenario_name": "adv_multi_ring_closing_right",
                "randseed": 1,
                "eval_time": 173.28538160026073,
                "team_1_hits": 404,
                "team_2_hits": 236,
                "team_1_wins": 1,
                "team_2_wins": 0,
                "team_1_deaths": 0,
                "team_2_deaths": 1
            },
            {
                "scenario_name": "adv_multi_two_rings_closing",
                "randseed": 1,
                "eval_time": 161.03979220008478,
                "team_1_hits": 254,
                "team_2_hits": 31,
                "team_1_wins": 1,
                "team_2_wins": 0,
                "team_1_deaths": 3,
                "team_2_deaths": 3
            },
            {
                "scenario_name": "avg_multi_ring_closing_both2",
                "randseed": 1,
                "eval_time": 38.150931500364095,
                "team_1_hits": 96,
                "team_2_hits": 96,
                "team_1_wins": 0,
                "team_2_wins": 0,
                "team_1_deaths": 3,
                "team_2_deaths": 1
            },
            {
                "scenario_name": "adv_multi_ring_closing_both_inside",
                "randseed": 1,
                "eval_time": 216.9065354000777,
                "team_1_hits": 463,
                "team_2_hits": 92,
                "team_1_wins": 1,
                "team_2_wins": 0,
                "team_1_deaths": 1,
                "team_2_deaths": 3
            },
            {
                "scenario_name": "adv_multi_ring_closing_both_inside_fast",
                "randseed": 1,
                "eval_time": 18.910330899991095,
                "team_1_hits": 97,
                "team_2_hits": 7,
                "team_1_wins": 1,
                "team_2_wins": 0,
                "team_1_deaths": 1,
                "team_2_deaths": 3
            },
            {
                "scenario_name": "Random Scenario 5",
                "randseed": 1,
                "eval_time": 13.60566130001098,
                "team_1_hits": 80,
                "team_2_hits": 21,
                "team_1_wins": 1,
                "team_2_wins": 0,
                "team_1_deaths": 0,
                "team_2_deaths": 0
            },
            {
                "scenario_name": "Random Scenario 6",
                "randseed": 1,
                "eval_time": 31.30954649997875,
                "team_1_hits": 121,
                "team_2_hits": 41,
                "team_1_wins": 1,
                "team_2_wins": 0,
                "team_1_deaths": 0,
                "team_2_deaths": 2
            },
            {
                "scenario_name": "Random Scenario 7",
                "randseed": 1,
                "eval_time": 7.031028000172228,
                "team_1_hits": 43,
                "team_2_hits": 24,
                "team_1_wins": 1,
                "team_2_wins": 0,
                "team_1_deaths": 0,
                "team_2_deaths": 0
            },
            {
                "scenario_name": "Random Scenario 8",
                "randseed": 1,
                "eval_time": 14.993252099957317,
                "team_1_hits": 101,
                "team_2_hits": 42,
                "team_1_wins": 1,
                "team_2_wins": 0,
                "team_1_deaths": 0,
                "team_2_deaths": 1
            },
            {
                "scenario_name": "Random Scenario 9",
                "randseed": 1,
                "eval_time": 5.6709178001619875,
                "team_1_hits": 41,
                "team_2_hits": 22,
                "team_1_wins": 1,
                "team_2_wins": 0,
                "team_1_deaths": 0,
                "team_2_deaths": 0
            },
            {
                "scenario_name": "Random Scenario 10",
                "randseed": 1,
                "eval_time": 14.782235499937087,
                "team_1_hits": 66,
                "team_2_hits": 49,
                "team_1_wins": 1,
                "team_2_wins": 0,
                "team_1_deaths": 0,
                "team_2_deaths": 0
            },
            {
                "scenario_name": "Random Scenario 11",
                "randseed": 1,
                "eval_time": 12.304164899978787,
                "team_1_hits": 78,
                "team_2_hits": 17,
                "team_1_wins": 1,
                "team_2_wins": 0,
                "team_1_deaths": 0,
                "team_2_deaths": 2
            },
            {
                "scenario_name": "Random Scenario 12",
                "randseed": 1,
                "eval_time": 31.01785090006888,
                "team_1_hits": 166,
                "team_2_hits": 32,
                "team_1_wins": 1,
                "team_2_wins": 0,
                "team_1_deaths": 0,
                "team_2_deaths": 2
            },
            {
                "scenario_name": "Random Scenario 13",
                "randseed": 1,
                "eval_time": 34.6455711000599,
                "team_1_hits": 210,
                "team_2_hits": 13,
                "team_1_wins": 1,
                "team_2_wins": 0,
                "team_1_deaths": 0,
                "team_2_deaths": 3
            },
            {
                "scenario_name": "Random Scenario 14",
                "randseed": 1,
                "eval_time": 23.67024639993906,
                "team_1_hits": 96,
                "team_2_hits": 32,
                "team_1_wins": 1,
                "team_2_wins": 0,
                "team_1_deaths": 2,
                "team_2_deaths": 1
            },
            {
                "scenario_name": "Random Scenario 15",
                "randseed": 1,
                "eval_time": 30.29766619997099,
                "team_1_hits": 181,
                "team_2_hits": 23,
                "team_1_wins": 1,
                "team_2_wins": 0,
                "team_1_deaths": 1,
                "team_2_deaths": 3
            },
            {
                "scenario_name": "Random Scenario 16",
                "randseed": 1,
                "eval_time": 17.768263000063598,
                "team_1_hits": 93,
                "team_2_hits": 58,
                "team_1_wins": 1,
                "team_2_wins": 0,
                "team_1_deaths": 0,
                "team_2_deaths": 0
            },
            {
                "scenario_name": "Random Scenario 17",
                "randseed": 1,
                "eval_time": 29.32125089969486,
                "team_1_hits": 147,
                "team_2_hits": 50,
                "team_1_wins": 1,
                "team_2_wins": 0,
                "team_1_deaths": 0,
                "team_2_deaths": 2
            },
            {
                "scenario_name": "Random Scenario 18",
                "randseed": 1,
                "eval_time": 66.6057449998334,
                "team_1_hits": 310,
                "team_2_hits": 20,
                "team_1_wins": 1,
                "team_2_wins": 0,
                "team_1_deaths": 1,
                "team_2_deaths": 3
            },
            {
                "scenario_name": "Random Scenario 19",
                "randseed": 1,
                "eval_time": 58.58089530002326,
                "team_1_hits": 339,
                "team_2_hits": 22,
                "team_1_wins": 1,
                "team_2_wins": 0,
                "team_1_deaths": 0,
                "team_2_deaths": 3
            },
            {
                "scenario_name": "Random Scenario 20",
                "randseed": 1,
                "eval_time": 83.25313140032813,
                "team_1_hits": 284,
                "team_2_hits": 18,
                "team_1_wins": 1,
                "team_2_wins": 0,
                "team_1_deaths": 2,
                "team_2_deaths": 3
            },
            {
                "scenario_name": "Random Scenario 21",
                "randseed": 1,
                "eval_time": 42.15339000010863,
                "team_1_hits": 156,
                "team_2_hits": 93,
                "team_1_wins": 1,
                "team_2_wins": 0,
                "team_1_deaths": 1,
                "team_2_deaths": 1
            },
            {
                "scenario_name": "Random Scenario 22",
                "randseed": 1,
                "eval_time": 38.30925599997863,
                "team_1_hits": 305,
                "team_2_hits": 8,
                "team_1_wins": 1,
                "team_2_wins": 0,
                "team_1_deaths": 0,
                "team_2_deaths": 3
            },
            {
                "scenario_name": "Random Scenario 23",
                "randseed": 1,
                "eval_time": 103.81677740020677,
                "team_1_hits": 466,
                "team_2_hits": 34,
                "team_1_wins": 1,
                "team_2_wins": 0,
                "team_1_deaths": 0,
                "team_2_deaths": 3
            },
            {
                "scenario_name": "Random Scenario 24",
                "randseed": 1,
                "eval_time": 16.2347813998349,
                "team_1_hits": 36,
                "team_2_hits": 20,
                "team_1_wins": 1,
                "team_2_wins": 0,
                "team_1_deaths": 3,
                "team_2_deaths": 3
            },
            {
                "scenario_name": "Random Scenario 25",
                "randseed": 1,
                "eval_time": 53.193350499961525,
                "team_1_hits": 316,
                "team_2_hits": 9,
                "team_1_wins": 1,
                "team_2_wins": 0,
                "team_1_deaths": 1,
                "team_2_deaths": 3
            },
            {
                "scenario_name": "Random Scenario 26",
                "randseed": 1,
                "eval_time": 65.18734570033848,
                "team_1_hits": 336,
                "team_2_hits": 17,
                "team_1_wins": 1,
                "team_2_wins": 0,
                "team_1_deaths": 1,
                "team_2_deaths": 3
            },
            {
                "scenario_name": "Random Scenario 27",
                "randseed": 1,
                "eval_time": 63.606753800064325,
                "team_1_hits": 377,
                "team_2_hits": 19,
                "team_1_wins": 1,
                "team_2_wins": 0,
                "team_1_deaths": 1,
                "team_2_deaths": 3
            },
            {
                "scenario_name": "Random Scenario 28",
                "randseed": 1,
                "eval_time": 35.36901080003008,
                "team_1_hits": 97,
                "team_2_hits": 22,
                "team_1_wins": 1,
                "team_2_wins": 0,
                "team_1_deaths": 3,
                "team_2_deaths": 3
            },
            {
                "scenario_name": "Random Scenario 29",
                "randseed": 1,
                "eval_time": 48.187229400034994,
                "team_1_hits": 342,
                "team_2_hits": 20,
                "team_1_wins": 1,
                "team_2_wins": 0,
                "team_1_deaths": 0,
                "team_2_deaths": 3
            },
            {
                "scenario_name": "Random Scenario 30",
                "randseed": 1,
                "eval_time": 64.9538873997517,
                "team_1_hits": 160,
                "team_2_hits": 12,
                "team_1_wins": 1,
                "team_2_wins": 0,
                "team_1_deaths": 3,
                "team_2_deaths": 3
            }
        ]
    }
]